wedos_wapi_client/__init__.py
wedos_wapi_client-0.1.1.dist-info/METADATA
wedos_wapi_client-0.1.1.dist-info/WHEEL
wedos_wapi_client-0.1.1.dist-info/RECORD
