Metadata-Version: 2.1
Name: wedos-wapi-client
Version: 0.1.1
Summary: WEDOS WAPI client
Home-page: https://github.com/qbsoftware/wedos-wapi-client
License: MIT
Author: Jakub Dorňák
Author-email: jakub.dornak@qbsoftware.cz
Requires-Python: >=3.10,<4.0
Classifier: Development Status :: 5 - Production/Stable
Classifier: Intended Audience :: Developers
Classifier: License :: OSI Approved :: MIT License
Classifier: Natural Language :: English
Classifier: Operating System :: POSIX
Classifier: Programming Language :: Python
Classifier: Programming Language :: Python :: 3
Classifier: Programming Language :: Python :: 3.10
Classifier: Programming Language :: Python :: 3.11
Classifier: Programming Language :: Python :: 3.12
Requires-Dist: requests
Project-URL: Repository, https://github.com/qbsoftware/wedos-wapi-client
